open_agent_api/__init__.py
open_agent_api/api_client.py
open_agent_api/api_response.py
open_agent_api/configuration.py
open_agent_api/exceptions.py
open_agent_api/models.py
open_agent_api/rest.py
open_agent_api/simple-models.py
open_agent_api/api/__init__.py
open_agent_api/api/account_api.py
open_agent_api/api/agents_api.py
open_agent_api/api/authentication_api.py
open_agent_api/api/billing_api.py
open_agent_api/api/chat_api.py
open_agent_api/api/default_api.py
open_agent_api/api/mcp_api.py
open_agent_api/api/subscription_api.py
open_agent_api/api/teams_api.py
open_agent_api/api/tools_api.py
open_agent_api/client/__init__.py
open_agent_api/client/api_client.py
open_agent_api/client/api_response.py
open_agent_api/client/configuration.py
open_agent_api/client/exceptions.py
open_agent_api/client/rest.py
open_agent_api/client/api/__init__.py
open_agent_api/client/api/account_api.py
open_agent_api/client/api/agents_api.py
open_agent_api/client/api/authentication_api.py
open_agent_api/client/api/billing_api.py
open_agent_api/client/api/chat_api.py
open_agent_api/client/api/default_api.py
open_agent_api/client/api/mcp_api.py
open_agent_api/client/api/subscription_api.py
open_agent_api/client/api/teams_api.py
open_agent_api/client/api/tools_api.py
open_agent_api/client/models/__init__.py
open_agent_api/client/models/account_balance_info.py
open_agent_api/client/models/account_info.py
open_agent_api/client/models/account_portal_session_created_response.py
open_agent_api/client/models/account_subscription_info.py
open_agent_api/client/models/account_subscription_purchase.py
open_agent_api/client/models/account_topup_request.py
open_agent_api/client/models/account_topup_response.py
open_agent_api/client/models/account_update_request.py
open_agent_api/client/models/account_usage_info.py
open_agent_api/client/models/account_usage_info_item.py
open_agent_api/client/models/agent.py
open_agent_api/client/models/agent_completion_chunk.py
open_agent_api-0.7.1.dist-info/METADATA
open_agent_api-0.7.1.dist-info/WHEEL
open_agent_api-0.7.1.dist-info/top_level.txt
open_agent_api-0.7.1.dist-info/RECORD
