Metadata-Version: 2.4
Name: open-agent-api
Version: 0.7.1
Summary: Open Agent API - Python client and models
Author: Sven Gericke
License: MIT
Project-URL: Homepage, https://github.com/sven-gericke/open-agent-api
Project-URL: Documentation, https://sven-gericke.github.io/open-agent-api/
Project-URL: Repository, https://github.com/sven-gericke/open-agent-api
Project-URL: Issues, https://github.com/sven-gericke/open-agent-api/issues
Keywords: api,client,openapi,agents
Classifier: Development Status :: 3 - Alpha
Classifier: Intended Audience :: Developers
Classifier: License :: OSI Approved :: MIT License
Classifier: Operating System :: OS Independent
Classifier: Programming Language :: Python :: 3
Classifier: Programming Language :: Python :: 3.8
Classifier: Programming Language :: Python :: 3.9
Classifier: Programming Language :: Python :: 3.10
Classifier: Programming Language :: Python :: 3.11
Classifier: Programming Language :: Python :: 3.12
Classifier: Topic :: Software Development :: Libraries :: Python Modules
Classifier: Topic :: Internet :: WWW/HTTP :: HTTP Servers
Requires-Python: >=3.11
Requires-Dist: requests>=2.28.0
Requires-Dist: pydantic>=2.0.0
Requires-Dist: typing-extensions>=4.5.0
Provides-Extra: dev
Requires-Dist: datamodel-code-generator>=0.25.0; extra == "dev"
Requires-Dist: openapi-generator-cli>=7.10.0; extra == "dev"
Requires-Dist: pre-commit>=3.0.0; extra == "dev"
Requires-Dist: pytest>=7.0.0; extra == "dev"
Requires-Dist: pytest-cov>=4.0.0; extra == "dev"
Requires-Dist: black>=23.0.0; extra == "dev"
Requires-Dist: isort>=5.12.0; extra == "dev"
Requires-Dist: flake8>=6.0.0; extra == "dev"
Requires-Dist: mypy>=1.5.0; extra == "dev"
